{
	"schemaVersion": 2,
	"type": "single-sprite-square-textured",
	"texture": "skybox:overworld/skies/sky_stars5.png",
	"blend": {"type" : "alpha"},
	"properties": {
		"priority": 403,
		"fade": {
			"startFadeIn": 2950,
			"endFadeIn": 3350,
			"startFadeOut": 3750,
			"endFadeOut": 4150
			},
		"rotation": {
			"rotationSpeedY": 1.0,
			"static": [0.0, 0.0, 0.0],
			"axis": [-63.48, 0.0, 0.0],
			"timeShift": [0, 18000, 0]
			},
		"transitionInDuration": 200,
		"transitionOutDuration": 200
		},
	"conditions": {
		"worlds": ["minecraft:overworld"],
		"weather": ["clear", "rain", "thunder", "snow"],
		"yRanges": [{"min": 255.0001, "max": 10000.0}],
		"loop": {
			"days": 5.0,
			"ranges": [{"min": 1, "max": 2}]
			}
		},
	"decorations": {
		"showSun": false,
		"showMoon": false,
		"showStars": false
		}
}
